check_celebrity/__init__.py
check_celebrity/celebrity_match.py
check_celebrity/main.py
check_celebrity/photo_validation.py
check_celebrity-1.0.6.dist-info/METADATA
check_celebrity-1.0.6.dist-info/WHEEL
check_celebrity-1.0.6.dist-info/top_level.txt
check_celebrity-1.0.6.dist-info/RECORD
