Metadata-Version: 2.1
Name: check-celebrity
Version: 1.0.6
Summary: Celebrity check Package
Requires-Dist: Deepface
Requires-Dist: mtcnn
Requires-Dist: keras
Requires-Dist: Tensorflow
Requires-Dist: numpy
Requires-Dist: opencv-python
Requires-Dist: Flask
Requires-Dist: keras-vggface
